bandoleers/__init__.py
bandoleers/args.py
bandoleers/prepit.py
bandoleers/waitfor.py
bandoleers-4.0.1.dist-info/LICENSE
bandoleers-4.0.1.dist-info/METADATA
bandoleers-4.0.1.dist-info/WHEEL
bandoleers-4.0.1.dist-info/entry_points.txt
bandoleers-4.0.1.dist-info/top_level.txt
bandoleers-4.0.1.dist-info/RECORD
